ReviewAutomationService/__init__.py
ReviewAutomationService/__main__.py
ReviewAutomationService/api.py
ReviewAutomationService/const.py
ReviewAutomationService/service.py
pih_rvw_auto-0.19.2.dist-info/METADATA
pih_rvw_auto-0.19.2.dist-info/WHEEL
pih_rvw_auto-0.19.2.dist-info/entry_points.txt
pih_rvw_auto-0.19.2.dist-info/top_level.txt
pih_rvw_auto-0.19.2.dist-info/RECORD
