Metadata-Version: 2.1
Name: pih-rvw_auto
Version: 0.19.2
Summary: PIH Review automation service package
Home-page: https://pacifichosp.com/
Author: Nikita Karachentsev
Author-email: it@pacifichosp.com
License: MIT
Requires-Dist: ipih
